chidori-0.1.26.dist-info/METADATA
chidori-0.1.26.dist-info/WHEEL
chidori/__init__.py
chidori/py.typed
chidori/_chidori.pyi
chidori/_chidori.abi3.so
chidori-0.1.26.dist-info/RECORD
